font_reducer/__init__.py
font_reducer-0.1.3.dist-info/LICENSE
font_reducer-0.1.3.dist-info/METADATA
font_reducer-0.1.3.dist-info/WHEEL
font_reducer-0.1.3.dist-info/top_level.txt
font_reducer-0.1.3.dist-info/RECORD
