Metadata-Version: 2.1
Name: font-reducer
Version: 0.1.3
Summary: A toolkit for reducing font size.
Home-page: UNKNOWN
Author: Eric Fan
Author-email: fjn0204@qq.com
License: UNKNOWN
Platform: UNKNOWN
Classifier: Programming Language :: Python :: 3
Classifier: License :: OSI Approved :: MIT License
Classifier: Operating System :: OS Independent
Requires-Dist: fonttools
